secciksym_package/__init__.py
secciksym_package/secciksym.py
secciksym-0.0.3.dist-info/LICENSE
secciksym-0.0.3.dist-info/METADATA
secciksym-0.0.3.dist-info/WHEEL
secciksym-0.0.3.dist-info/top_level.txt
secciksym-0.0.3.dist-info/RECORD
